odoo/addons/web_field_numeric_formatting/README.rst
odoo/addons/web_field_numeric_formatting/__init__.py
odoo/addons/web_field_numeric_formatting/__manifest__.py
odoo/addons/web_field_numeric_formatting/i18n/it.po
odoo/addons/web_field_numeric_formatting/i18n/web_field_numeric_formatting.pot
odoo/addons/web_field_numeric_formatting/readme/CONTRIBUTORS.rst
odoo/addons/web_field_numeric_formatting/readme/DESCRIPTION.rst
odoo/addons/web_field_numeric_formatting/static/description/icon.png
odoo/addons/web_field_numeric_formatting/static/description/index.html
odoo/addons/web_field_numeric_formatting/static/src/components/float_field.esm.js
odoo/addons/web_field_numeric_formatting/static/src/components/integer_field.esm.js
odoo/addons/web_field_numeric_formatting/static/src/components/list_renderer.esm.js
odoo/addons/web_field_numeric_formatting/static/tests/field_tests.esm.js
odoo_addon_web_field_numeric_formatting-16.0.1.0.0.5.dist-info/METADATA
odoo_addon_web_field_numeric_formatting-16.0.1.0.0.5.dist-info/WHEEL
odoo_addon_web_field_numeric_formatting-16.0.1.0.0.5.dist-info/top_level.txt
odoo_addon_web_field_numeric_formatting-16.0.1.0.0.5.dist-info/RECORD
