Metadata-Version: 2.1
Name: odoo-addon-web-field-numeric-formatting
Version: 16.0.1.0.0.5
Summary: Allow to render float and integer fields without thousands separator
Home-page: https://github.com/OCA/web
Author: Opener B.V., Odoo Community Association (OCA)
Author-email: support@odoo-community.org
License: LGPL-3
Platform: UNKNOWN
Classifier: Programming Language :: Python
Classifier: Framework :: Odoo
Classifier: Framework :: Odoo :: 16.0
Classifier: License :: OSI Approved :: GNU Lesser General Public License v3 (LGPLv3)
Requires-Python: >=3.10
Requires-Dist: odoo <16.1dev,>=16.0a
